<?xml version="1.0" encoding="UTF-8"?>
<root>
  <magicslider>
    <item>
      <title><![CDATA[Slide Demo 1]]></title>
      <identifier><![CDATA[slide]]></identifier>
      <config><![CDATA[{"magicslider_id":"1","title":"Slide Demo 1","status":"1","mobile":"1","portrait":"1","landscape":"1","tablet":"1","notebook":"1","desktop":"1","visible":"1","vertical":"false","infinite":"true","autoplay":"true","arrows":"true","dots":"true","rows":"1","speed":"400","autoplay-Speed":"6000","padding":"0","media_gallery":{"images":{"gvf4o2i837t4vvr1er":{"position":"4","media_type":"image","video_provider":"","file":"\/s\/l\/slide1.jpg","value_id":"","label":"Alotheme DigitalStore","link":"http:\/\/alothemes.com\/","caption":"<div class=\"container figcaption\">\r\n\t<div class=\"text-slide text-slide1\">\r\n\t\t<h3 class=\"caption1\">ELECTRONICS T.V.<\/h3>\r\n\t\t<h3 class=\"caption2\">On Rent-Rentalwala-3005<\/h3>\r\n                <h3 class=\"caption3\">For your  Smart TV<\/h3>\r\n                <h3 class=\"caption4\"><a href=\"#\" class=\"btn-shop\">Shop Now<\/a><\/h3>\r\n\t<\/div>\r\n<\/div>\r\n","disabled":"0","removed":"","video_url":"","video_title":"","video_description":"","video_metadata":"","role":""},"r7i50hiw9hfgpd9gv8":{"position":"5","media_type":"image","video_provider":"","file":"\/s\/l\/slide2.jpg","value_id":"","label":"Alotheme DigitalStore","link":"http:\/\/alothemes.com\/","caption":"<div class=\"container figcaption\">\r\n\t<div class=\"text-slide text-slide2\">\r\n\t\t<h3 class=\"caption1 black\">Re-Furbished Laptops<\/h3>\r\n                <h3 class=\"caption3 black\">With 1 year warranty.<\/h3>\r\n                <h3 class=\"caption4\"><a href=\"#\" class=\"btn-shop\">Shop Now<\/a><\/h3>\r\n\t<\/div>\r\n<\/div>\r\n","disabled":"0","removed":"","video_url":"","video_title":"","video_description":"","video_metadata":"","role":""},"an3f124fl8nafwadnw":{"position":"6","media_type":"image","video_provider":"","file":"\/s\/l\/slide3.jpg","value_id":"","label":"Alotheme DigitalStore","link":"http:\/\/alothemes.com\/","caption":"<div class=\"container figcaption\">\r\n\t<div class=\"text-slide text-slide3\">\r\n\t\t<h3 class=\"caption1 black\">Professional Security<\/h3>\r\n\t\t<h3 class=\"caption2 black\">Camera<\/h3>\r\n                <h3 class=\"caption3 black\">CamGuardian U-tec Professionation<\/h3>\r\n                <h3 class=\"caption4\"><a href=\"#\" class=\"btn-shop\">Shop Now<\/a><\/h3>\r\n\t<\/div>\r\n<\/div>\r\n","disabled":"0","removed":"","video_url":"","video_title":"","video_description":"","video_metadata":"","role":""}}}}]]></config>
      <status><![CDATA[1]]></status>
    </item>
    <item>
      <title><![CDATA[Slide Demo 2]]></title>
      <identifier><![CDATA[slide2]]></identifier>
      <config><![CDATA[{"magicslider_id":"2","title":"Slide Demo 2","status":"1","mobile":"1","portrait":"1","landscape":"1","tablet":"1","notebook":"1","desktop":"1","visible":"1","vertical":"false","infinite":"true","autoplay":"true","arrows":"false","dots":"true","rows":"1","speed":"400","autoplay-Speed":"6000","padding":"0","media_gallery":{"images":{"0v0pn1hkf47qi8t86p":{"position":"1","media_type":"image","video_provider":"","file":"\/s\/l\/slide1-demo2.jpg","value_id":"","label":"Alotheme DigitalStore","link":"http:\/\/alothemes.com\/","caption":"<div class=\"container figcaption\">\r\n\t<div class=\"text-slide text-slide1\">\r\n\t\t<h3 class=\"caption1 black\">ELECTRONICS T.V.<\/h3>\r\n                <h3 class=\"caption3 black\">For your  Smart TV<\/h3>\r\n                <h3 class=\"caption4\"><a href=\"#\" class=\"btn-shop\">Shop Now<\/a><\/h3>\r\n\t<\/div>\r\n<\/div>\r\n","disabled":"0","removed":"","video_url":"","video_title":"","video_description":"","video_metadata":"","role":""},"wjreigshgdcjqi6o4v":{"position":"4","media_type":"image","video_provider":"","file":"\/s\/l\/slide2-demo2_1.jpg","value_id":"","label":"Alotheme DigitalStore","link":"http:\/\/alothemes.com\/","caption":"<div class=\"container figcaption\">\r\n\t<div class=\"text-slide text-slide2\">\r\n\t\t<h3 class=\"caption1\">Control Your Home<\/h3>\r\n                <h3 class=\"caption3\">For your  Smart TV<\/h3>\r\n                <h3 class=\"caption4\"><a href=\"#\" class=\"btn-shop\">Shop Now<\/a><\/h3>\r\n\t<\/div>\r\n<\/div>\r\n","disabled":"0","removed":"","video_url":"","video_title":"","video_description":"","video_metadata":"","role":""},"a284c8g4lc84uil2d0":{"position":"5","media_type":"image","video_provider":"","file":"\/s\/l\/slide3-demo2.jpg","value_id":"","label":"Alotheme DigitalStore","link":"http:\/\/alothemes.com\/","caption":"<div class=\"container figcaption\">\r\n\t<div class=\"text-slide text-slide3\">\r\n\t\t<h3 class=\"caption1\">By Your Own Watchs<\/h3>\r\n                <h3 class=\"caption3\">No Up-front costs.<br>Launch your store now!<\/h3>\r\n                <h3 class=\"caption4\"><a href=\"#\" class=\"btn-shop\">Shop Now<\/a><\/h3>\r\n\t<\/div>\r\n<\/div>\r\n","disabled":"0","removed":"","video_url":"","video_title":"","video_description":"","video_metadata":"","role":""}}}}]]></config>
      <status><![CDATA[1]]></status>
    </item>
    <item>
      <title><![CDATA[Slide Demo 3]]></title>
      <identifier><![CDATA[slide3]]></identifier>
      <config><![CDATA[{"magicslider_id":"3","title":"Slide Demo 3","status":"1","mobile":"1","portrait":"1","landscape":"1","tablet":"1","notebook":"1","desktop":"1","visible":"1","vertical":"false","infinite":"true","autoplay":"true","arrows":"false","dots":"true","rows":"1","speed":"400","autoplay-Speed":"6000","padding":"0","media_gallery":{"images":{"5hq861ucd0fhsqo4pl":{"position":"2","media_type":"image","video_provider":"","file":"\/s\/l\/slide1-demo3.jpg","value_id":"","label":"Alotheme DigitalStore","link":"http:\/\/alothemes.com\/","caption":"<div class=\"container figcaption\">\r\n\t<div class=\"text-slide text-slide1\">\r\n\t\t<h3 class=\"caption1 gray\">World Leader in home<\/h3>\r\n\t\t<h3 class=\"caption2 black\">ELECTRONICS Fridge<\/h3>\r\n                <h3 class=\"caption3 gray\">For your  Smart Fridge.<\/h3>\r\n                <h3 class=\"caption4\"><a href=\"#\" class=\"btn-shop\">Shop Now<\/a><\/h3>\r\n\t<\/div>\r\n<\/div>\r\n","disabled":"0","removed":"","video_url":"","video_title":"","video_description":"","video_metadata":"","role":""},"iu01g37h0jt1o54oow":{"position":"3","media_type":"image","video_provider":"","file":"\/s\/l\/slide2-demo3.jpg","value_id":"","label":"Alotheme DigitalStore","link":"http:\/\/alothemes.com\/","caption":"<div class=\"container figcaption\">\r\n\t<div class=\"text-slide text-slide2\">\r\n\t\t<h3 class=\"caption1 black\">Resolutionary<\/h3>\r\n                <h3 class=\"caption3 gray\">The New iPad.<\/h3>\r\n                <h3 class=\"caption4\"><a href=\"#\" class=\"btn-shop\">Shop Now<\/a><\/h3>\r\n\t<\/div>\r\n<\/div>\r\n","disabled":"0","removed":"","video_url":"","video_title":"","video_description":"","video_metadata":"","role":""},"l4wvblmv2rf8gabkp6":{"position":"4","media_type":"image","video_provider":"","file":"\/s\/l\/slide3-demo3.jpg","value_id":"","label":"Alotheme DigitalStore","link":"http:\/\/alothemes.com\/","caption":"<div class=\"container figcaption\">\r\n\t<div class=\"text-slide text-slide3\">\r\n\t\t<h3 class=\"caption1 black\">Innovative<\/h3>\r\n\t\t<h3 class=\"caption2 red\">Smarter Brighter<\/h3>\r\n                <h3 class=\"caption3 gray\">40\u2019\u2019 Skyhi Smart Package.<\/h3>\r\n                <h3 class=\"caption4\"><a href=\"#\" class=\"btn-shop\">Shop Now<\/a><\/h3>\r\n\t<\/div>\r\n<\/div>\r\n","disabled":"0","removed":"","video_url":"","video_title":"","video_description":"","video_metadata":"","role":""}}}}]]></config>
      <status><![CDATA[1]]></status>
    </item>
    <item>
      <title><![CDATA[Slide Demo 4]]></title>
      <identifier><![CDATA[slide4]]></identifier>
      <config><![CDATA[{"magicslider_id":"4","title":"Slide Demo 4","status":"1","mobile":"1","portrait":"1","landscape":"1","tablet":"1","notebook":"1","desktop":"1","visible":"1","vertical":"false","infinite":"true","autoplay":"true","arrows":"false","dots":"true","rows":"1","speed":"400","autoplay-Speed":"6000","padding":"0","media_gallery":{"images":{"st51t4o32u2m12i7r3":{"position":"1","media_type":"image","video_provider":"","file":"\/s\/l\/slide1-demo4.jpg","value_id":"","label":"Alotheme DigitalStore","link":"http:\/\/alothemes.com\/","caption":"<div class=\"container figcaption\">\r\n\t<div class=\"text-slide text-slide1\">\r\n\t\t<h3 class=\"caption1\">Resolutionary<\/h3>\r\n                <h3 class=\"caption3\">The New iPad.<\/h3>\r\n                <h3 class=\"caption4\"><a href=\"#\" class=\"btn-shop\">Shop Now<\/a><\/h3>\r\n\t<\/div>\r\n<\/div>\r\n","disabled":"0","removed":"","video_url":"","video_title":"","video_description":"","video_metadata":"","role":""},"e037pkak4cd2l6897b":{"position":"2","media_type":"image","video_provider":"","file":"\/s\/l\/slide2-demo4.jpg","value_id":"","label":"Alotheme DigitalStore","link":"http:\/\/alothemes.com\/","caption":"<div class=\"container figcaption\">\r\n\t<div class=\"text-slide text-slide2\">\r\n\t\t<h3 class=\"caption1 black\">The new imac<\/h3>\r\n                <h3 class=\"caption3 black\">The New iPad.<\/h3>\r\n                <h3 class=\"caption4\"><a href=\"#\" class=\"btn-shop\">Shop Now<\/a><\/h3>\r\n\t<\/div>\r\n<\/div>\r\n","disabled":"0","removed":"","video_url":"","video_title":"","video_description":"","video_metadata":"","role":""},"p46bc96cja4v63t7g3":{"position":"3","media_type":"image","video_provider":"","file":"\/s\/l\/slide3-demo4.jpg","value_id":"","label":"Alotheme DigitalStore","link":"http:\/\/alothemes.com\/","caption":"<div class=\"container figcaption\">\r\n\t<div class=\"text-slide text-slide3\">\r\n\t\t<h3 class=\"caption1\">Resolutionary<\/h3>\r\n                <h3 class=\"caption3\">The New iPad.<\/h3>\r\n                <h3 class=\"caption4\"><a href=\"#\" class=\"btn-shop\">Shop Now<\/a><\/h3>\r\n\t<\/div>\r\n<\/div>\r\n","disabled":"0","removed":"","video_url":"","video_title":"","video_description":"","video_metadata":"","role":""}}}}]]></config>
      <status><![CDATA[1]]></status>
    </item>
    <item>
      <title><![CDATA[Slide Demo 5]]></title>
      <identifier><![CDATA[slide5]]></identifier>
      <config><![CDATA[{"magicslider_id":"5","title":"Slide Demo 5","status":"1","mobile":"1","portrait":"1","landscape":"1","tablet":"1","notebook":"1","desktop":"1","visible":"1","vertical":"false","infinite":"true","autoplay":"true","arrows":"true","dots":"true","rows":"1","speed":"300","autoplay-Speed":"6000","padding":"0","media_gallery":{"images":{"vi3mt78b4tp0fqjngj":{"position":"1","media_type":"image","video_provider":"","file":"\/s\/l\/slide1-demo5.jpg","value_id":"","label":"Alotheme DigitalStore","link":"http:\/\/alothemes.com\/","caption":"<div class=\"container figcaption\">\r\n\t<div class=\"text-slide text-slide1\">\r\n\t\t<h3 class=\"caption1 black\">Home Digital Accessories<\/h3>\r\n                <h3 class=\"caption3 black\">Speaker, Audio System<\/h3>\r\n                <h3 class=\"caption4\"><a href=\"#\" class=\"btn-shop\">Shop Now<\/a><\/h3>\r\n\t<\/div>\r\n<\/div>\r\n","disabled":"0","removed":"","video_url":"","video_title":"","video_description":"","video_metadata":"","role":""},"wrcu9d8hgd76aakwce":{"position":"2","media_type":"image","video_provider":"","file":"\/s\/l\/slide2-demo5.jpg","value_id":"","label":"Alotheme DigitalStore","link":"http:\/\/alothemes.com\/","caption":"<div class=\"container figcaption\">\r\n\t<div class=\"text-slide text-slide2\">\r\n\t\t<h3 class=\"caption1 gray\">13 - inch<\/h3>\r\n\t\t<h3 class=\"caption2\">Macbook Pro 2017<\/h3>\r\n                <h3 class=\"caption3\">A touch of genius<\/h3>\r\n                <h3 class=\"caption4\"><a href=\"#\" class=\"btn-shop\">Shop Now<\/a><\/h3>\r\n\t<\/div>\r\n<\/div>\r\n","disabled":"0","removed":"","video_url":"","video_title":"","video_description":"","video_metadata":"","role":""},"vvo53qdc54gdtiw387":{"position":"3","media_type":"image","video_provider":"","file":"\/s\/l\/slide3-demo5.jpg","value_id":"","label":"Alotheme DigitalStore","link":"http:\/\/alothemes.com\/","caption":"<div class=\"container figcaption\">\r\n\t<div class=\"text-slide text-slide3\">\r\n\t\t<h3 class=\"caption1 gray\">Tech Online<\/h3>\r\n\t\t<h3 class=\"caption2 black\">New iMac Pro 2016<\/h3>\r\n                <h3 class=\"caption4\"><a href=\"#\" class=\"btn-shop\">Shop Now<\/a><\/h3>\r\n\t<\/div>\r\n<\/div>\r\n","disabled":"0","removed":"","video_url":"","video_title":"","video_description":"","video_metadata":"","role":""}}}}]]></config>
      <status><![CDATA[1]]></status>
    </item>
  </magicslider>
</root>
